LICENSE
README.rst
distribute_setup.py
requirements.txt
setup.cfg
setup.py
pycic/__init__.py
pycic/base.py
pycic/category.py
pycic/exceptions.py
pycic/group.py
pycic/report.py
pycic.egg-info/PKG-INFO
pycic.egg-info/SOURCES.txt
pycic.egg-info/dependency_links.txt
pycic.egg-info/requires.txt
pycic.egg-info/top_level.txt