Metadata-Version: 1.0
Name: pycic
Version: 0.1.2
Summary: Python library for accesing CIC (Centro Integracion Ciudadana) APIs
Home-page: UNKNOWN
Author: Milton Mazzarri
Author-email: milmazz@gmail.com
License: MIT
Keywords: cic
Platform: UNKNOWN
